wucai/__init__.py
wucai-0.1.2.dist-info/LICENSE
wucai-0.1.2.dist-info/METADATA
wucai-0.1.2.dist-info/WHEEL
wucai-0.1.2.dist-info/top_level.txt
wucai-0.1.2.dist-info/RECORD
