Metadata-Version: 2.2
Name: wucai
Version: 0.1.2
Summary: 五彩 Python API | python API for wucai ( https://www.wucainote.com , https://marker.dotalk.cn )
Home-page: https://github.com/Benature/wucai
Author: Benature Wang
Author-email: benature246@gmail.com
Classifier: Programming Language :: Python :: 3.7
Classifier: License :: OSI Approved :: MIT License
Classifier: Operating System :: OS Independent
Requires-Python: >=3.7
License-File: LICENSE
Requires-Dist: requests
Requires-Dist: bs4
Requires-Dist: lxml
Dynamic: author
Dynamic: author-email
Dynamic: classifier
Dynamic: description
Dynamic: description-content-type
Dynamic: home-page
Dynamic: requires-dist
Dynamic: requires-python
Dynamic: summary
